win32more/Microsoft/Web/WebView2/Core/__init__.py
win32more/dll/arm64/Microsoft.Web.WebView2.Core.dll
win32more/dll/x64/Microsoft.Web.WebView2.Core.dll
win32more/dll/x86/Microsoft.Web.WebView2.Core.dll
win32more_microsoft_web_webview2-0.8.1.0.3650.58.dist-info/METADATA
win32more_microsoft_web_webview2-0.8.1.0.3650.58.dist-info/WHEEL
win32more_microsoft_web_webview2-0.8.1.0.3650.58.dist-info/licenses/LICENSE (Microsoft.Web.WebView2).txt
win32more_microsoft_web_webview2-0.8.1.0.3650.58.dist-info/RECORD
