Metadata-Version: 2.4
Name: win32more-Microsoft.Web.WebView2
Version: 0.8.1.0.3650.58
License-File: LICENSE (Microsoft.Web.WebView2).txt
Requires-Dist: win32more-core==0.8.*
